multilint.py
pymultilint-1.1.0.dist-info/LICENSE
pymultilint-1.1.0.dist-info/METADATA
pymultilint-1.1.0.dist-info/WHEEL
pymultilint-1.1.0.dist-info/entry_points.txt
pymultilint-1.1.0.dist-info/RECORD
