Metadata-Version: 2.1
Name: pymultilint
Version: 1.1.0
Summary: Utility tying multiple code quality tools together
Home-page: https://github.com/gkze/multilint
License: MIT
Keywords: lint,code-quality,tools
Author: George Kontridze
Author-email: george.kontridze@gmail.com
Requires-Python: >=3.8,<4.0
Classifier: License :: OSI Approved :: MIT License
Classifier: Programming Language :: Python :: 3
Classifier: Programming Language :: Python :: 3.8
Classifier: Programming Language :: Python :: 3.9
Classifier: Programming Language :: Python :: 3.10
Classifier: Programming Language :: Python :: 3.11
Requires-Dist: autoflake (>=2.0,<3.0)
Requires-Dist: black (>=23.3,<24.0)
Requires-Dist: isort (>=5.12,<6.0)
Requires-Dist: mypy (>=1.2,<2.0)
Requires-Dist: pydocstyle (>=6.3,<7.0)
Requires-Dist: pylint (>=2.17,<3.0)
Requires-Dist: pyupgrade (>=3.3,<4.0)
Requires-Dist: toml (>=0.10,<0.11)
Project-URL: Documentation, https://gkze.github.io/multilint/multilint.html
Project-URL: Repository, https://github.com/gkze/multilint
